setup.py
torrent_cli.py
torrent_client/__init__.py
torrent_client/file_structure.py
torrent_client/models.py
torrent_client/utils.py
torrent_client.egg-info/PKG-INFO
torrent_client.egg-info/SOURCES.txt
torrent_client.egg-info/dependency_links.txt
torrent_client.egg-info/requires.txt
torrent_client.egg-info/top_level.txt
torrent_client/algorithms/__init__.py
torrent_client/algorithms/announcer.py
torrent_client/algorithms/downloader.py
torrent_client/algorithms/peer_manager.py
torrent_client/algorithms/speed_measurer.py
torrent_client/algorithms/torrent_manager.py
torrent_client/algorithms/uploader.py
torrent_client/control/__init__.py
torrent_client/control/client.py
torrent_client/control/formatters.py
torrent_client/control/manager.py
torrent_client/control/server.py
torrent_client/network/__init__.py
torrent_client/network/peer_tcp_client.py
torrent_client/network/peer_tcp_server.py
torrent_client/network/tracker_clients/__init__.py
torrent_client/network/tracker_clients/base.py
torrent_client/network/tracker_clients/http.py
torrent_client/network/tracker_clients/udp.py